LICENSE
README.md
setup.py
rick_vfs/__init__.py
rick_vfs/utils.py
rick_vfs/version.py
rick_vfs/vfs.py
rick_vfs.egg-info/PKG-INFO
rick_vfs.egg-info/SOURCES.txt
rick_vfs.egg-info/dependency_links.txt
rick_vfs.egg-info/not-zip-safe
rick_vfs.egg-info/requires.txt
rick_vfs.egg-info/top_level.txt
rick_vfs/local/__init__.py
rick_vfs/local/local.py
rick_vfs/s3/__init__.py
rick_vfs/s3/s3.py
tests/__init__.py
tests/local/__init__.py
tests/local/test_vfs.py
tests/local/test_volume.py
tests/s3/__init__.py
tests/s3/test_vfs.py
tests/s3/test_volume.py